Quote2Image/Quote2Image.py
Quote2Image/__init__.py
Quote2Image-0.0.5.dist-info/LICENSE
Quote2Image-0.0.5.dist-info/METADATA
Quote2Image-0.0.5.dist-info/WHEEL
Quote2Image-0.0.5.dist-info/top_level.txt
Quote2Image-0.0.5.dist-info/RECORD
