Metadata-Version: 2.1
Name: Quote2Image
Version: 0.0.5
Summary: A python module to convert text quotes into graphical images
Home-page: https://github.com/NotCookey/Quote2Image
Author: NotCookey
Author-email: kanao.nishimiya@gmail.com
Keywords: quotes,images,text,conversion,quote2image,quote to image,quote text to image
Classifier: Programming Language :: Python :: 3
Classifier: Operating System :: Unix
Classifier: License :: OSI Approved :: GNU General Public License v3 (GPLv3)
Classifier: Operating System :: MacOS :: MacOS X
Classifier: Operating System :: Microsoft :: Windows
License-File: LICENSE
Requires-Dist: Pillow (==9.2.0)
